README.rst
setup.cfg
setup.py
oglhslack/__init__.py
oglhslack/oglhslack.py
oglhslack.egg-info/PKG-INFO
oglhslack.egg-info/SOURCES.txt
oglhslack.egg-info/dependency_links.txt
oglhslack.egg-info/requires.txt
oglhslack.egg-info/top_level.txt