Metadata-Version: 1.1
Name: oglhslack
Version: 1.0.0
Summary: A Slack chat bot for Opengear Lighthouse
Home-page: https://github.com/opengear/oglhslack
Author: Lighthouse Team
Author-email: engineering@opengear.com
License: UNKNOWN
Download-URL: https://github.com/opengear/oglhslack/archive/v1.0.0.tar.gz
Keywords: api,opengear,lighthouse,slackbot
Platform: UNKNOWN
Classifier: Development Status :: 5 - Production/Stable
Classifier: Intended Audience :: System Administrators
Classifier: Programming Language :: Python :: 2
Classifier: Programming Language :: Python :: 3
